{
    "skeleton": {
        "hash": "wjo0jftsuoY",
        "spine": "4.1.24",
        "x": -551.5,
        "y": -250.62,
        "width": 1103,
        "height": 519.12,
        "images": "./images/Cloud4/",
        "audio": "E:/ps/闲云角色预热"
    },
    "bones": [
        {
            "name": "root"
        },
        {
            "name": "bone",
            "parent": "root",
            "length": 106.87,
            "rotation": 86.93,
            "x": 354.12,
            "y": 81.19
        },
        {
            "name": "bone2",
            "parent": "root",
            "length": 119.03,
            "rotation": 86.33,
            "x": 171.81,
            "y": 61.49
        },
        {
            "name": "bone3",
            "parent": "root",
            "length": 86.36,
            "rotation": 117.13,
            "x": 100.03,
            "y": 76.1
        },
        {
            "name": "bone4",
            "parent": "root",
            "length": 82.71,
            "rotation": 126.25,
            "x": 42.23,
            "y": 4.32
        },
        {
            "name": "bone5",
            "parent": "root",
            "length": 91.1,
            "rotation": 122.47,
            "x": -85.45,
            "y": -14.1
        },
        {
            "name": "bone6",
            "parent": "root",
            "length": 90.87,
            "rotation": 128.47,
            "x": -137.54,
            "y": -33.15
        },
        {
            "name": "bone7",
            "parent": "root",
            "length": 76.44,
            "rotation": 111.45,
            "x": -213.13,
            "y": -53.48
        },
        {
            "name": "bone8",
            "parent": "root",
            "length": 67.3,
            "rotation": 109.29,
            "x": -304.6,
            "y": -73.17
        },
        {
            "name": "bone9",
            "parent": "root",
            "length": 88.19,
            "rotation": 141.73,
            "x": -368.76,
            "y": -84.61
        },
        {
            "name": "bone10",
            "parent": "root",
            "length": 91.05,
            "rotation": 165.87,
            "x": -432.28,
            "y": -111.28
        }
    ],
    "slots": [
        {
            "name": "云2",
            "bone": "root",
            "attachment": "云2"
        }
    ],
    "skins": [
        {
            "name": "default",
            "attachments": {
                "云2": {
                    "云2": {
                        "type": "mesh",
                        "uvs": [
                            0.0003,
                            0.76752,
                            0.06867,
                            0.79045,
                            0.1196,
                            0.89506,
                            0.18239,
                            0.96671,
                            0.27169,
                            0.95811,
                            0.35331,
                            0.90796,
                            0.44541,
                            0.89219,
                            0.54098,
                            0.88933,
                            0.58215,
                            0.80478,
                            0.64633,
                            0.69587,
                            0.68959,
                            0.57263,
                            0.74191,
                            0.49812,
                            0.79703,
                            0.43077,
                            0.79842,
                            0.34049,
                            0.86261,
                            0.27027,
                            0.91423,
                            0.22585,
                            0.9833,
                            0.27457,
                            1,
                            0.16136,
                            0.96098,
                            0.10261,
                            0.90028,
                            0.06249,
                            0.81935,
                            0.06535,
                            0.77749,
                            0.08685,
                            0.76703,
                            0,
                            0.69447,
                            0,
                            0.63726,
                            0.02523,
                            0.5661,
                            0.06105,
                            0.51029,
                            0.13127,
                            0.49006,
                            0.22585,
                            0.42169,
                            0.22585,
                            0.34215,
                            0.28747,
                            0.28634,
                            0.34049,
                            0.22634,
                            0.4279,
                            0.18169,
                            0.48092,
                            0.10146,
                            0.49525,
                            0.0282,
                            0.56977,
                            0,
                            0.66435,
                            0.0889,
                            0.67581,
                            0.17332,
                            0.63855,
                            0.24448,
                            0.62565,
                            0.2975,
                            0.51388,
                            0.36029,
                            0.43793,
                            0.44541,
                            0.40067,
                            0.52424,
                            0.38921,
                            0.56052,
                            0.26741,
                            0.63168,
                            0.19002,
                            0.69656,
                            0.15707,
                            0.8354,
                            0.18716,
                            0.76563,
                            0.26024,
                            0.71191,
                            0.32902,
                            0.65749,
                            0.4451,
                            0.60587,
                            0.54971,
                            0.55285,
                            0.65002,
                            0.48238,
                            0.64285,
                            0.40215,
                            0.68584,
                            0.34843,
                            0.75606,
                            0.28773,
                            0.82341,
                            0.21518,
                            0.81338,
                            0.15588,
                            0.78615
                        ],
                        "triangles": [
                            36,
                            34,
                            33,
                            35,
                            34,
                            36,
                            1,
                            0,
                            35,
                            57,
                            36,
                            37,
                            36,
                            1,
                            35,
                            1,
                            36,
                            57,
                            2,
                            1,
                            57,
                            3,
                            57,
                            56,
                            2,
                            57,
                            3,
                            37,
                            33,
                            32,
                            36,
                            33,
                            37,
                            57,
                            37,
                            56,
                            32,
                            31,
                            38,
                            37,
                            32,
                            38,
                            56,
                            37,
                            38,
                            55,
                            56,
                            38,
                            54,
                            55,
                            38,
                            4,
                            56,
                            55,
                            3,
                            56,
                            4,
                            39,
                            30,
                            40,
                            31,
                            30,
                            39,
                            38,
                            31,
                            39,
                            54,
                            39,
                            53,
                            38,
                            39,
                            54,
                            5,
                            54,
                            6,
                            55,
                            54,
                            5,
                            4,
                            55,
                            5,
                            30,
                            29,
                            40,
                            39,
                            40,
                            53,
                            6,
                            53,
                            52,
                            54,
                            53,
                            6,
                            29,
                            28,
                            41,
                            40,
                            29,
                            41,
                            53,
                            40,
                            41,
                            53,
                            41,
                            52,
                            41,
                            28,
                            27,
                            41,
                            27,
                            42,
                            50,
                            42,
                            49,
                            52,
                            41,
                            42,
                            51,
                            52,
                            42,
                            50,
                            51,
                            42,
                            9,
                            50,
                            10,
                            51,
                            50,
                            9,
                            8,
                            51,
                            9,
                            7,
                            52,
                            51,
                            7,
                            51,
                            8,
                            6,
                            52,
                            7,
                            43,
                            26,
                            25,
                            43,
                            25,
                            44,
                            27,
                            26,
                            43,
                            42,
                            27,
                            43,
                            42,
                            43,
                            49,
                            21,
                            45,
                            23,
                            21,
                            23,
                            22,
                            24,
                            23,
                            45,
                            44,
                            25,
                            24,
                            44,
                            24,
                            45,
                            47,
                            45,
                            21,
                            48,
                            45,
                            47,
                            44,
                            45,
                            48,
                            12,
                            48,
                            13,
                            49,
                            44,
                            48,
                            43,
                            44,
                            49,
                            11,
                            48,
                            12,
                            49,
                            48,
                            11,
                            10,
                            49,
                            11,
                            50,
                            49,
                            10,
                            46,
                            20,
                            19,
                            15,
                            19,
                            18,
                            46,
                            19,
                            15,
                            14,
                            46,
                            15,
                            17,
                            15,
                            18,
                            16,
                            15,
                            17,
                            21,
                            20,
                            46,
                            46,
                            47,
                            21,
                            13,
                            46,
                            14,
                            13,
                            47,
                            46,
                            13,
                            48,
                            47
                        ],
                        "vertices": [
                            1,
                            10,
                            107.39,
                            60.43,
                            1,
                            2,
                            8,
                            -21.61,
                            188.9,
                            0.00185,
                            10,
                            31.25,
                            53.95,
                            0.99815,
                            4,
                            7,
                            -72.19,
                            250.17,
                            0.01731,
                            8,
                            -93.19,
                            154.44,
                            0.08678,
                            9,
                            -39.1,
                            131.61,
                            0.1418,
                            10,
                            -36.94,
                            94.71,
                            0.75411,
                            5,
                            6,
                            -37.88,
                            301.89,
                            0.0068,
                            7,
                            -133.32,
                            199.78,
                            0.09837,
                            8,
                            -152.38,
                            101.78,
                            0.24644,
                            9,
                            -117.3,
                            118.92,
                            0.21227,
                            10,
                            -113.5,
                            115.11,
                            0.43611,
                            7,
                            4,
                            -27.97,
                            385.16,
                            0.00197,
                            5,
                            -106.33,
                            264.87,
                            0.00188,
                            6,
                            -95.54,
                            221.9,
                            0.0759,
                            7,
                            -165.04,
                            106.42,
                            0.3072,
                            8,
                            -180.56,
                            7.29,
                            0.3413,
                            9,
                            -191.77,
                            54.28,
                            0.11745,
                            10,
                            -207.88,
                            86.58,
                            0.1543,
                            7,
                            4,
                            -59.5,
                            296.63,
                            0.04822,
                            5,
                            -131.94,
                            174.45,
                            0.05451,
                            6,
                            -130.47,
                            134.66,
                            0.2659,
                            7,
                            -172.9,
                            12.77,
                            0.40426,
                            8,
                            -184.89,
                            -86.59,
                            0.17708,
                            9,
                            -245.77,
                            -22.63,
                            0.02074,
                            10,
                            -288.62,
                            38.48,
                            0.02929,
                            8,
                            2,
                            -286.4,
                            214.13,
                            0.00241,
                            4,
                            -112.74,
                            209.71,
                            0.26645,
                            5,
                            -179.34,
                            84.21,
                            0.21233,
                            6,
                            -187.04,
                            49.86,
                            0.30905,
                            7,
                            -202.16,
                            -84.87,
                            0.18205,
                            8,
                            -210.45,
                            -185.26,
                            0.02688,
                            9,
                            -320.27,
                            -92.19,
                            8e-05,
                            10,
                            -385.05,
                            5.47,
                            0.00076,
                            6,
                            2,
                            -278.11,
                            109.02,
                            0.03259,
                            4,
                            -173.84,
                            123.79,
                            0.53052,
                            5,
                            -234.64,
                            -5.56,
                            0.22136,
                            6,
                            -251.42,
                            -33.63,
                            0.1633,
                            7,
                            -239.28,
                            -183.55,
                            0.05169,
                            8,
                            -243.83,
                            -285.27,
                            0.00054,
                            5,
                            2,
                            -229.9,
                            66.62,
                            0.08985,
                            4,
                            -164.08,
                            60.33,
                            0.62735,
                            5,
                            -220.71,
                            -68.23,
                            0.16493,
                            6,
                            -244.12,
                            -97.42,
                            0.09556,
                            7,
                            -213.62,
                            -242.41,
                            0.02231,
                            7,
                            1,
                            -196.41,
                            182.47,
                            0.00032,
                            2,
                            -167,
                            -0.29,
                            0.33303,
                            3,
                            -189.33,
                            28.05,
                            0.00734,
                            4,
                            -158.78,
                            -31.35,
                            0.59026,
                            5,
                            -209.38,
                            -159.36,
                            0.04644,
                            6,
                            -242.38,
                            -189.23,
                            0.02115,
                            7,
                            -185.07,
                            -329.69,
                            0.00146,
                            6,
                            1,
                            -127.77,
                            138.37,
                            0.03807,
                            2,
                            -97.9,
                            -43.66,
                            0.70674,
                            3,
                            -152.19,
                            -44.59,
                            0.01084,
                            4,
                            -133.63,
                            -108.96,
                            0.24019,
                            5,
                            -179.16,
                            -235.14,
                            0.00278,
                            6,
                            -220.25,
                            -267.76,
                            0.00137,
                            3,
                            1,
                            -84.73,
                            82.88,
                            0.21942,
                            2,
                            -54.27,
                            -98.7,
                            0.75344,
                            4,
                            -135.49,
                            -179.16,
                            0.02714,
                            2,
                            1,
                            -45.36,
                            24.11,
                            0.47857,
                            2,
                            -14.29,
                            -157.05,
                            0.52143,
                            2,
                            1,
                            3.13,
                            25.16,
                            0.72543,
                            2,
                            34.19,
                            -155.48,
                            0.27457,
                            1,
                            1,
                            44.57,
                            -43.52,
                            1,
                            1,
                            1,
                            71.44,
                            -99.1,
                            1,
                            1,
                            1,
                            49.39,
                            -176.57,
                            1,
                            1,
                            1,
                            111.08,
                            -191.72,
                            1,
                            1,
                            1,
                            140.28,
                            -147.05,
                            1,
                            1,
                            1,
                            158.21,
                            -79.04,
                            1,
                            2,
                            1,
                            151.9,
                            10.01,
                            0.95961,
                            2,
                            183.11,
                            -169.05,
                            0.04039,
                            2,
                            1,
                            137.91,
                            55.5,
                            0.61737,
                            2,
                            168.64,
                            -123.72,
                            0.38263,
                            2,
                            1,
                            183.86,
                            69.52,
                            0.38063,
                            2,
                            214.44,
                            -109.21,
                            0.61937,
                            3,
                            1,
                            179.58,
                            149.44,
                            0.14806,
                            2,
                            209.31,
                            -29.35,
                            0.84487,
                            3,
                            119.03,
                            -189.61,
                            0.00707,
                            3,
                            1,
                            162.67,
                            211.72,
                            0.01516,
                            2,
                            191.75,
                            32.76,
                            0.81242,
                            3,
                            135.74,
                            -127.27,
                            0.17242,
                            2,
                            2,
                            167.53,
                            109.86,
                            0.2884,
                            3,
                            154.42,
                            -48.65,
                            0.7116,
                            4,
                            2,
                            125.96,
                            168.88,
                            0.01416,
                            3,
                            148.93,
                            23.34,
                            0.9118,
                            4,
                            174.45,
                            -89.64,
                            0.07315,
                            5,
                            126.97,
                            -195.54,
                            0.00088,
                            3,
                            3,
                            113.91,
                            66.36,
                            0.47583,
                            4,
                            146.69,
                            -41.61,
                            0.44511,
                            5,
                            96.11,
                            -149.45,
                            0.07906,
                            3,
                            3,
                            148.3,
                            133.47,
                            0.02628,
                            4,
                            191.28,
                            19.21,
                            0.38765,
                            5,
                            136.59,
                            -85.82,
                            0.58607,
                            4,
                            4,
                            216.48,
                            109.52,
                            0.02076,
                            5,
                            155.78,
                            5.95,
                            0.63824,
                            6,
                            138.06,
                            -63,
                            0.33757,
                            7,
                            141.73,
                            -97.61,
                            0.00344,
                            4,
                            5,
                            164.81,
                            73.18,
                            0.07898,
                            6,
                            154.07,
                            2.91,
                            0.56391,
                            7,
                            137.74,
                            -29.9,
                            0.35204,
                            8,
                            127.14,
                            -117.53,
                            0.00508,
                            3,
                            6,
                            158.49,
                            83.92,
                            0.00563,
                            7,
                            118.25,
                            48.86,
                            0.48797,
                            8,
                            104.7,
                            -39.56,
                            0.5064,
                            3,
                            7,
                            109.76,
                            105.11,
                            0.00477,
                            8,
                            94.09,
                            16.33,
                            0.80671,
                            9,
                            44.89,
                            -85.4,
                            0.18852,
                            2,
                            8,
                            116.06,
                            102.4,
                            0.02616,
                            9,
                            109.59,
                            -24.55,
                            0.97384,
                            2,
                            9,
                            148.24,
                            56.91,
                            0.23105,
                            10,
                            103.47,
                            -50.07,
                            0.76895,
                            2,
                            9,
                            141.21,
                            116.06,
                            0.00132,
                            10,
                            121.24,
                            6.78,
                            0.99868,
                            2,
                            9,
                            60.41,
                            60.15,
                            0.09605,
                            10,
                            24.64,
                            -11.2,
                            0.90395,
                            2,
                            8,
                            17.25,
                            53.01,
                            0.16074,
                            9,
                            -0.3,
                            -13.23,
                            0.83926,
                            3,
                            7,
                            12.1,
                            69.07,
                            0.23608,
                            8,
                            -2.14,
                            -23.37,
                            0.76302,
                            10,
                            -135.19,
                            -79.22,
                            0.0009,
                            2,
                            6,
                            73.51,
                            51.2,
                            0.07884,
                            7,
                            46.58,
                            -7.31,
                            0.92116,
                            2,
                            5,
                            76.87,
                            32.45,
                            0.41731,
                            6,
                            62.35,
                            -28.4,
                            0.58269,
                            2,
                            4,
                            100.11,
                            53.63,
                            0.44425,
                            5,
                            43.34,
                            -57.49,
                            0.55575,
                            2,
                            3,
                            18.64,
                            72.8,
                            0.16673,
                            4,
                            53.65,
                            -20.13,
                            0.83327,
                            2,
                            3,
                            58.61,
                            7.36,
                            0.96722,
                            4,
                            82.73,
                            -91.08,
                            0.03278,
                            2,
                            2,
                            103.05,
                            33.23,
                            0.75773,
                            3,
                            59.79,
                            -81.44,
                            0.24227,
                            2,
                            1,
                            95.48,
                            142.62,
                            0.13294,
                            2,
                            125.29,
                            -37.05,
                            0.86706,
                            1,
                            1,
                            87.53,
                            -11.16,
                            1,
                            2,
                            1,
                            44.23,
                            63.58,
                            0.622,
                            2,
                            74.88,
                            -116.62,
                            0.378,
                            2,
                            1,
                            4.17,
                            120.78,
                            0.20623,
                            2,
                            34.22,
                            -59.86,
                            0.79377,
                            4,
                            1,
                            -61.28,
                            177.38,
                            0.01608,
                            2,
                            -31.82,
                            -3.95,
                            0.83664,
                            3,
                            -75.09,
                            -44.32,
                            0.05584,
                            4,
                            -57.47,
                            -120.91,
                            0.09144,
                            7,
                            1,
                            -120.42,
                            231.24,
                            0.00017,
                            2,
                            -91.53,
                            49.28,
                            0.31605,
                            3,
                            -99.12,
                            31.98,
                            0.09802,
                            4,
                            -69.1,
                            -41.77,
                            0.56511,
                            5,
                            -119.2,
                            -163.85,
                            0.01455,
                            6,
                            -153.16,
                            -203.12,
                            0.00599,
                            7,
                            -95.7,
                            -316.85,
                            0.00012,
                            6,
                            2,
                            -149.03,
                            104.19,
                            0.08485,
                            3,
                            -120.39,
                            108.59,
                            0.00199,
                            4,
                            -77.95,
                            37.24,
                            0.71101,
                            5,
                            -133.24,
                            -85.59,
                            0.14176,
                            6,
                            -158.95,
                            -123.82,
                            0.05116,
                            7,
                            -124.45,
                            -242.72,
                            0.00924,
                            6,
                            2,
                            -150.17,
                            182,
                            0.00637,
                            4,
                            -28.88,
                            97.64,
                            0.45725,
                            5,
                            -88.27,
                            -22.08,
                            0.38662,
                            6,
                            -107.58,
                            -65.37,
                            0.12159,
                            7,
                            -92.45,
                            -171.79,
                            0.02792,
                            8,
                            -97.55,
                            -267.99,
                            0.00025,
                            6,
                            4,
                            4.83,
                            182.66,
                            0.08661,
                            5,
                            -60.23,
                            64.97,
                            0.21445,
                            6,
                            -70.6,
                            18.28,
                            0.49356,
                            7,
                            -81.58,
                            -80.98,
                            0.1882,
                            8,
                            -90.1,
                            -176.84,
                            0.01678,
                            10,
                            -311.73,
                            -90.34,
                            0.00041,
                            7,
                            4,
                            9.47,
                            252.74,
                            0.03086,
                            5,
                            -60.23,
                            135.21,
                            0.04213,
                            6,
                            -63.26,
                            88.13,
                            0.32512,
                            7,
                            -95.01,
                            -12.04,
                            0.46234,
                            8,
                            -106.12,
                            -108.45,
                            0.12162,
                            9,
                            -191.02,
                            -83.33,
                            0.00645,
                            10,
                            -263.48,
                            -39.31,
                            0.01147,
                            7,
                            4,
                            19.89,
                            328.11,
                            0.00488,
                            5,
                            -54.8,
                            211.1,
                            0.0047,
                            6,
                            -49.92,
                            163.04,
                            0.10626,
                            7,
                            -104.19,
                            63.49,
                            0.40429,
                            8,
                            -118.14,
                            -33.32,
                            0.33898,
                            9,
                            -160.86,
                            -13.47,
                            0.06704,
                            10,
                            -207.39,
                            12.11,
                            0.07385,
                            5,
                            6,
                            4.09,
                            222.35,
                            0.01166,
                            7,
                            -69.91,
                            136.01,
                            0.13358,
                            8,
                            -86.61,
                            40.44,
                            0.37292,
                            9,
                            -94.69,
                            31.87,
                            0.25201,
                            10,
                            -128.46,
                            26.43,
                            0.22983,
                            5,
                            6,
                            56.23,
                            264.46,
                            6e-05,
                            7,
                            -32.39,
                            191.54,
                            0.01583,
                            8,
                            -51.21,
                            97.35,
                            0.10626,
                            9,
                            -34.29,
                            60.91,
                            0.33843,
                            10,
                            -61.46,
                            28.22,
                            0.53942
                        ],
                        "hull": 36,
                        "edges": [
                            0,
                            2,
                            2,
                            4,
                            4,
                            6,
                            6,
                            8,
                            8,
                            10,
                            10,
                            12,
                            12,
                            14,
                            14,
                            16,
                            16,
                            18,
                            18,
                            20,
                            20,
                            22,
                            22,
                            24,
                            24,
                            26,
                            26,
                            28,
                            28,
                            30,
                            30,
                            32,
                            32,
                            34,
                            34,
                            36,
                            36,
                            38,
                            38,
                            40,
                            40,
                            42,
                            42,
                            44,
                            44,
                            46,
                            46,
                            48,
                            48,
                            50,
                            50,
                            52,
                            52,
                            54,
                            54,
                            56,
                            56,
                            58,
                            58,
                            60,
                            60,
                            62,
                            62,
                            64,
                            64,
                            66,
                            66,
                            68,
                            68,
                            70,
                            0,
                            70
                        ],
                        "width": 1103,
                        "height": 537
                    }
                }
            }
        }
    ],
    "animations": {
        "Loop": {},
        "Stay": {}
    },
    "extra": {
        "bone10": {
            "rootBoneName": "bone10",
            "animation": {
                "default": {
                    "name": "default",
                    "mode": 1,
                    "rotateCenter": 0,
                    "rotateTime": 6,
                    "rotateRange": 17,
                    "rotateOffset": 0,
                    "childOffset": 0.25,
                    "spring": 0,
                    "affectByLevel": 0.1,
                    "springLevel": 0
                }
            }
        },
        "bone9": {
            "rootBoneName": "bone9",
            "animation": {
                "default": {
                    "name": "default",
                    "mode": 1,
                    "rotateCenter": 0,
                    "rotateTime": 6,
                    "rotateRange": 17,
                    "rotateOffset": 0.4,
                    "childOffset": 0.25,
                    "spring": 0,
                    "affectByLevel": 0.1,
                    "springLevel": 0
                }
            }
        },
        "bone8": {
            "rootBoneName": "bone8",
            "animation": {
                "default": {
                    "name": "default",
                    "mode": 1,
                    "rotateCenter": 0,
                    "rotateTime": 6,
                    "rotateRange": 17,
                    "rotateOffset": 0.8,
                    "childOffset": 0.25,
                    "spring": 0,
                    "affectByLevel": 0.1,
                    "springLevel": 0
                }
            }
        },
        "bone5": {
            "rootBoneName": "bone5",
            "animation": {
                "default": {
                    "name": "default",
                    "mode": 1,
                    "rotateCenter": 0,
                    "rotateTime": 6,
                    "rotateRange": 17,
                    "rotateOffset": 2,
                    "childOffset": 0.25,
                    "spring": 0,
                    "affectByLevel": 0.1,
                    "springLevel": 0
                }
            }
        },
        "bone6": {
            "rootBoneName": "bone6",
            "animation": {
                "default": {
                    "name": "default",
                    "mode": 1,
                    "rotateCenter": 0,
                    "rotateTime": 6,
                    "rotateRange": 17,
                    "rotateOffset": 1.6,
                    "childOffset": 0.25,
                    "spring": 0,
                    "affectByLevel": 0.1,
                    "springLevel": 0
                }
            }
        },
        "bone7": {
            "rootBoneName": "bone7",
            "animation": {
                "default": {
                    "name": "default",
                    "mode": 1,
                    "rotateCenter": 0,
                    "rotateTime": 6,
                    "rotateRange": 17,
                    "rotateOffset": 1.2,
                    "childOffset": 0.25,
                    "spring": 0,
                    "affectByLevel": 0.1,
                    "springLevel": 0
                }
            }
        },
        "bone2": {
            "rootBoneName": "bone2",
            "animation": {
                "default": {
                    "name": "default",
                    "mode": 1,
                    "rotateCenter": 0,
                    "rotateTime": 6,
                    "rotateRange": 17,
                    "rotateOffset": 3.2,
                    "childOffset": 0.25,
                    "spring": 0,
                    "affectByLevel": 0.1,
                    "springLevel": 0
                }
            }
        },
        "bone3": {
            "rootBoneName": "bone3",
            "animation": {
                "default": {
                    "name": "default",
                    "mode": 1,
                    "rotateCenter": 0,
                    "rotateTime": 6,
                    "rotateRange": 17,
                    "rotateOffset": 2.8,
                    "childOffset": 0.25,
                    "spring": 0,
                    "affectByLevel": 0.1,
                    "springLevel": 0
                }
            }
        },
        "bone4": {
            "rootBoneName": "bone4",
            "animation": {
                "default": {
                    "name": "default",
                    "mode": 1,
                    "rotateCenter": 0,
                    "rotateTime": 6,
                    "rotateRange": 17,
                    "rotateOffset": 2.4,
                    "childOffset": 0.25,
                    "spring": 0,
                    "affectByLevel": 0.1,
                    "springLevel": 0
                }
            }
        },
        "bone": {
            "rootBoneName": "bone",
            "animation": {
                "default": {
                    "name": "default",
                    "mode": 1,
                    "rotateCenter": 0,
                    "rotateTime": 6,
                    "rotateRange": 17,
                    "rotateOffset": 3.6,
                    "childOffset": 0.25,
                    "spring": 0,
                    "affectByLevel": 0.1,
                    "springLevel": 0
                }
            }
        }
    },
    "extraSlot": {},
    "extraConfig": {
        "timeScale": 1
    }
}